README.rst
setup.py
commit_coverage/__init__.py
commit_coverage/__main__.py
commit_coverage.egg-info/PKG-INFO
commit_coverage.egg-info/SOURCES.txt
commit_coverage.egg-info/dependency_links.txt
commit_coverage.egg-info/entry_points.txt
commit_coverage.egg-info/top_level.txt